cosmosim/__init__.py
cosmosim/astrotime.py
cosmosim/bodies.py
cosmosim/collision.py
cosmosim/constants.py
cosmosim/core.py
cosmosim/ephemeris.py
cosmosim/orbit.py
cosmosim/relativity.py
cosmosim/simulation.py
cosmosim/spectra.py
cosmosim/visual.py
cosmosim2025-1.0.0.dist-info/licenses/LICENSE
cosmosim2025-1.0.0.dist-info/METADATA
cosmosim2025-1.0.0.dist-info/WHEEL
cosmosim2025-1.0.0.dist-info/top_level.txt
cosmosim2025-1.0.0.dist-info/RECORD
