Metadata-Version: 2.4
Name: cosmosim2025
Version: 1.0.0
Summary: A modular astronomy and orbital simulation library.
Author: YourName
Author-email: your_email@example.com
License: MIT
Requires-Python: >=3.8
License-File: LICENSE
Requires-Dist: matplotlib
Dynamic: author
Dynamic: author-email
Dynamic: license
Dynamic: license-file
Dynamic: requires-dist
Dynamic: requires-python
Dynamic: summary
